phenocellpy/__init__.py
phenocellpy/cell_volume.py
phenocellpy/phases.py
phenocellpy/phenotypes.py
phenocellpy/utils/__init__.py
phenocellpy/utils/add_cycle_to_object.py
phenocellpy/utils/cc3d/__init__.py
phenocellpy-0.1.0.dist-info/METADATA
phenocellpy-0.1.0.dist-info/WHEEL
phenocellpy-0.1.0.dist-info/licenses/LICENSE
phenocellpy-0.1.0.dist-info/RECORD
