Metadata-Version: 2.4
Name: phenocellpy
Version: 0.1.0
Summary: Tools for phenotypic characterization of cell behavior
Project-URL: Homepage, https://github.com/OpenVT/PhenoCellPy
Project-URL: Publication, https://doi.org/10.1101/2023.04.12.535625
Author: Juliano Ferrari Gianlupi
License: BSD 3-Clause License
License-File: LICENSE
Requires-Python: >=3.8
Requires-Dist: numpy
Requires-Dist: scipy
